nano_banana_2/__init__.py
nano_banana_2-1767173.744.68.dist-info/licenses/LICENSE
nano_banana_2-1767173.744.68.dist-info/METADATA
nano_banana_2-1767173.744.68.dist-info/WHEEL
nano_banana_2-1767173.744.68.dist-info/top_level.txt
nano_banana_2-1767173.744.68.dist-info/RECORD
